LICENSE
README.md
setup.py
nicorbtt/__init__.py
nicorbtt/nicorbtt.py
nicorbtt.egg-info/PKG-INFO
nicorbtt.egg-info/SOURCES.txt
nicorbtt.egg-info/dependency_links.txt
nicorbtt.egg-info/top_level.txt