Metadata-Version: 2.1
Name: nicorbtt
Version: 0.0.1
Summary: just for fun...
Home-page: https://github.com/nicorbtt/nicorbtt
Author: Nico Rubattu
Author-email: iamnicown@gmail.com
License: UNKNOWN
Platform: UNKNOWN
Classifier: Programming Language :: Python :: 3
Classifier: License :: OSI Approved :: MIT License
Classifier: Operating System :: OS Independent
License-File: LICENSE
